penguinSDK-1.0.2.dist-info/DESCRIPTION.rst
penguinSDK-1.0.2.dist-info/LICENSE.txt
penguinSDK-1.0.2.dist-info/METADATA
penguinSDK-1.0.2.dist-info/RECORD
penguinSDK-1.0.2.dist-info/WHEEL
penguinSDK-1.0.2.dist-info/metadata.json
penguinSDK-1.0.2.dist-info/top_level.txt
penguinsdk/__init__.py
penguinsdk/client.py
penguinsdk/endpoints.py
penguinsdk/exceptions.py
penguinsdk/publisher.py
penguinsdk/uploader.py
penguinsdk/utils.py
penguinsdk/video_cats.py
penguinsdk/auth/__init__.py
penguinsdk/auth/credential.py
penguinsdk/auth/oauth2.py
penguinsdk/doclinks/__init__.py
penguinsdk/doclinks/api_3rd_party.py
penguinsdk/doclinks/api_content_site.py
penguinsdk/doclinks/auth.py
