Metadata-Version: 2.0
Name: penguinSDK
Version: 1.0.2
Summary: python sdk to query API from penguin(腾讯内容开放平台)
Home-page: UNKNOWN
Author: Yufu Luo
Author-email: fisherman.luo@gmail.com
License: MIT
Platform: UNKNOWN
Classifier: License :: OSI Approved :: MIT License
Classifier: Programming Language :: Python
Classifier: Programming Language :: Python :: 2.7
Classifier: Programming Language :: Python :: 3
Classifier: Programming Language :: Python :: 3.4
Classifier: Programming Language :: Python :: 3.5
Classifier: Programming Language :: Python :: 3.6
Classifier: Programming Language :: Python :: Implementation :: CPython
Requires-Dist: doclink (>=1.0.7)
